setup.py
PyWeka.egg-info/PKG-INFO
PyWeka.egg-info/SOURCES.txt
PyWeka.egg-info/dependency_links.txt
PyWeka.egg-info/requires.txt
PyWeka.egg-info/top_level.txt
pyweka/MachineLearning.py
pyweka/__init__.py