Metadata-Version: 1.0
Name: PyWeka
Version: 0.3dev
Summary: PyWeka, a python WEKA wrapper.
Home-page: http://www-helix.stanford.edu
Author: Nicholas P. Tatonetti & Guy Haskin Fernald
Author-email: nick.tatonetti@stanford.edu & guyhf@stanford.edu
License: UNKNOWN
Platform: UNKNOWN
